{
  "homeInfo": {
    "title": "首页",
    "href": "page/my_welcome.html?t=1"
  },
  "logoInfo": {
    "title": "物流系统",
    "image": "images/logo.png",
    "href": ""
  },
  "menuInfo": [
    {
      "title": "管理中心",
      "icon": "fa fa-address-book",
      "href": "",
      "target": "_self",
      "child": [
        {
          "title": "基本管理",
          "href": "",
          "icon": "fa fa-home",
          "target": "_self",
          "child": [
            {
              "title": "员工管理",
              "href": "page/emp.html",
              "icon": "fa fa-tachometer",
              "target": "_self"
            },
            {
              "title": "车辆管理",
              "href": "page/car.html",
              "icon": "fa fa-tachometer",
              "target": "_self"
            }
          ]
        },
        {
          "title": "业务管理",
          "href": "",
          "icon": "fa fa-home",
          "target": "_self",
          "child": [
            {
              "title": "运单管理",
              "href": "page/waybill.html",
              "icon": "fa fa-tachometer",
              "target": "_self"
            },
            {
              "title": "财务管理",
              "href": "",
              "icon": "fa fa-tachometer",
              "target": "_self",
              "child": [
                {
                  "title": "支出管理",
                  "href": "page/finance.html",
                  "icon": "fa fa-tachometer",
                  "target": "_self"
                }
              ]
            }
          ]
        }
      ]
    },
    {
      "title": "组件管理",
      "icon": "fa fa-lemon-o",
      "href": "",
      "target": "_self",
      "child": [
        {
          "title": "图标列表",
          "href": "page/icon.html",
          "icon": "fa fa-dot-circle-o",
          "target": "_self"
        }
      ]
    }
  ]
}